Metadata-Version: 2.1
Name: api-bible-sdk
Version: 0.1.1
Summary: An SDK to use the api.bible API
Home-page: https://gitlab.com/coldkey.21/api_bible_python_sdk
Author: Matthew Birky
Author-email: coldkey.21@gmail.com
License: MIT
Platform: UNKNOWN
Classifier: License :: OSI Approved :: MIT License
Classifier: Programming Language :: Python
Classifier: Programming Language :: Python :: 3
Classifier: Programming Language :: Python :: 3.6
Classifier: Programming Language :: Python :: Implementation :: CPython
Classifier: Programming Language :: Python :: Implementation :: PyPy
Requires-Python: >=3.7.0
